setup.py
mailscraper/__init__.py
mailscraper.egg-info/PKG-INFO
mailscraper.egg-info/SOURCES.txt
mailscraper.egg-info/dependency_links.txt
mailscraper.egg-info/not-zip-safe
mailscraper.egg-info/top_level.txt