Metadata-Version: 1.0
Name: mailscraper
Version: 0.1
Summary: Webcrawler will enter your domain and scan every page of your website, extracting page titles, descriptions, keywords, and links etc,.
Home-page: http://github.com/username/mailscraper
Author: JALEEL AKBERUDDIN BASHA
Author-email: jaleelbasha0@gmail.com
License: JaleelBasha
Platform: UNKNOWN
